katana_meter/__init__.py
katana_meter/api.py
katana_meter/cli.py
katana_meter/core.py
katana_meter/gui.py
katana_meter-0.1.2.dist-info/licenses/LICENSE
katana_meter-0.1.2.dist-info/METADATA
katana_meter-0.1.2.dist-info/WHEEL
katana_meter-0.1.2.dist-info/entry_points.txt
katana_meter-0.1.2.dist-info/top_level.txt
katana_meter-0.1.2.dist-info/RECORD
