Metadata-Version: 2.4
Name: katana-meter
Version: 0.1.2
Summary: Analyzer-only LUFS / True Peak / ΔE audio meter (Research License)
Author: Katana Project
Classifier: License :: Other/Proprietary License
Classifier: Programming Language :: Python :: 3
Classifier: Operating System :: OS Independent
Classifier: Topic :: Multimedia :: Sound/Audio :: Analysis
Requires-Python: >=3.9
License-File: LICENSE
Dynamic: license-file
